{"geocoded_waypoints": [{"geocoder_status": "OK", "place_id": "ChIJM3Ac_1y5QIYRMfbBax7xv2E", "types": ["establishment", "point_of_interest", "primary_school", "school"]}, {"geocoder_status": "OK", "place_id": "ChIJ9_tphxzHQIYRIMyPy_d3VZU", "types": ["establishment", "point_of_interest"]}], "routes": [{"bounds": {"northeast": {"lat": 29.80413, "lng": -95.3187203}, "southwest": {"lat": 29.79499329999999, "lng": -95.45463819999999}}, "copyrights": "Map data \u00a92022", "legs": [{"arrival_time": {"text": "4:04pm", "time_zone": "America/Chicago", "value": 1642025097}, "departure_time": {"text": "3:14pm", "time_zone": "America/Chicago", "value": 1642022088}, "distance": {"text": "8.7 mi", "value": 13960}, "duration": {"text": "50 mins", "value": 3009}, "end_address": "4400 W 18th St, Houston, TX 77092, USA", "end_location": {"lat": 29.8019199, "lng": -95.45428179999999}, "start_address": "3830 Pickfair St, Houston, TX 77026, USA", "start_location": {"lat": 29.79499329999999, "lng": -95.3187203}, "steps": [{"distance": {"text": "0.9 mi", "value": 1520}, "duration": {"text": "19 mins", "value": 1161}, "end_location": {"lat": 29.8005867, "lng": -95.32834079999999}, "html_instructions": "Walk to Hirsch Rd @ Cavalcade St", "polyline": {"points": "uiztD~|wdQuA@eB?sED@dC?P@fEB~ID`JB~I@tE?f@?rBG@@P?RG?I?[B_@DUBGBMBi@NIBm@NC?]HUDq@Hm@BE?m@@C?yEBM?O@M?k@?"}, "start_location": {"lat": 29.79499329999999, "lng": -95.3187203}, "steps": [{"distance": {"text": "0.1 mi", "value": 222}, "duration": {"text": "3 mins", "value": 163}, "end_location": {"lat": 29.7969855, "lng": -95.3187564}, "html_instructions": "Head <b>north</b> on <b>Pickfair St</b> toward <b>Crane St</b>", "polyline": {"points": "uiztD~|wdQuA@eB?sED"}, "start_location": {"lat": 29.79499329999999, "lng": -95.3187203}, "travel_mode": "WALKING"}, {"distance": {"text": "0.5 mi", "value": 875}, "duration": {"text": "11 mins", "value": 654}, "end_location": {"lat": 29.7969249, "lng": -95.3278594}, "html_instructions": "Turn <b>left</b> onto <b>Crane St</b>", "maneuver": "turn-left", "polyline": {"points": "evztDf}wdQ@dC?P@fEB~ID`JB~I@tE?f@?rBG@@P?R"}, "start_location": {"lat": 29.7969855, "lng": -95.3187564}, "travel_mode": "WALKING"}, {"distance": {"text": "341 ft", "value": 104}, "duration": {"text": "1 min", "value": 84}, "end_location": {"lat": 29.7977888, "lng": -95.328069}, "html_instructions": "Turn <b>right</b> onto <b>Broyles St</b>", "maneuver": "turn-right", "polyline": {"points": "wuztDbvydQG?I?[B_@DUBGBMBi@NIB"}, "start_location": {"lat": 29.7969249, "lng": -95.3278594}, "travel_mode": "WALKING"}, {"distance": {"text": "0.2 mi", "value": 315}, "duration": {"text": "4 mins", "value": 257}, "end_location": {"lat": 29.8005867, "lng": -95.32834079999999}, "html_instructions": "Continue straight onto <b>Hirsch Rd</b>", "maneuver": "straight", "polyline": {"points": "e{ztDlwydQm@NC?]HUDq@Hm@BE?m@@C?yEBM?O@M?k@?"}, "start_location": {"lat": 29.7977888, "lng": -95.328069}, "travel_mode": "WALKING"}, {"distance": {"text": "13 ft", "value": 4}, "duration": {"text": "1 min", "value": 3}, "end_location": {"lat": 29.8005867, "lng": -95.32834079999999}, "html_instructions": "Turn <b>left</b><div style=\"font-size:0.9em\">Destination will be on the right</div>", "maneuver": "turn-left", "polyline": {"points": "ul{tDbyydQ"}, "start_location": {"lat": 29.8005867, "lng": -95.32834079999999}, "travel_mode": "WALKING"}], "travel_mode": "WALKING"}, {"distance": {"text": "7.7 mi", "value": 12342}, "duration": {"text": "30 mins", "value": 1772}, "end_location": {"lat": 29.80163, "lng": -95.454342}, "html_instructions": "Bus towards Memorial City", "polyline": {"points": "yl{tDdyydQ?It@??n@?j@@bD?p@@hA?X?x@DvCFpD?rA@zBGvAEpAGjBARC\\K`AEb@]fBKb@EPGVYdAUdAMx@W|AOjAMx@EZGd@WbBKj@Ib@EVAFIf@ADKn@Kz@In@K|@SdBK|@Gb@K~@AHW|Bc@jEo@fFWlBK|@EVSbBQpAGr@Mp@Eb@CNOrAKdBCf@?HAx@?xB@d@@j@?pA@nA?X@dB?T@fAB~D@bD@ZBbEBzB@fAGrAAXGvA@vD@xC@^@tD@x@?V?v@?l@?\\BpD@nB?fA@jA?tA?T?\\?lA@nA?tA@dA?Z@bA?pB@vDAlBAV?LANAT?RAXCR?@CXQ|@Kf@Sz@ENOr@CRE\\Cb@KfCARCpAAv@AXCf@?DAT?LAHCfAAd@?D?lB?h@?VBjC?lB?x@@z@@fB?fD@fDE`BA|@?HA\\@V?lA@L?\\?x@?V@j@@t@?L?JB`@@T@NBN@N@V?f@@f@?`A?r@?L?xBAP?JALAPANIbAEb@?TAR?V?fH?p@@vD@xAC^C^CRA@ETC\\Af@?P?P?LA`@@\\BpA?^@j@?H@tA?n@?b@@b@?X?P?V@`A?v@@dA?V?vA@T?lB@jB@tA?XB|E?~A@zB@nB?V?V@t@?L?R?L@R?N?f@?h@@|@?\\?d@?b@@n@?pA@|B?d@?`@@t@?T?pA@v@@rA?v@@bD@~@?nA@H?tB@^@dC?P?j@@x@?x@?t@@P?dA@|A?\\?^@dC@zB?xA?N@V?fA@`ABfE?tABtJ?pB@rA?r@?H?|@?jB?@?j@@h@AL?\\?J@f@?|B?h@?|@?n@?N?|G?J@tE?d@@dC?p@AL@J?V@P@H?B?D@F@HBH@JDPDLDLDHDJDJHLFHFHLL?@TVTVn@v@NRh@h@NPVX^f@BJBFBFf@v@P`@DZDVBT@F?D@F?H?P@P?X?N?F?j@@pAIpB@f@?V?fA?j@?V@h@AjA?h@@~@?b@@^Af@@d@?X?bA?jA?b@@nC?J?d@Aj@?v@?P@dB?jA?bC?`A?\\@dH?`D?dC@fE?jD?T@`F@vB?jD?vC?X?`E@V@zCAb@?fAAX@fB@fA?T@|B?l@A~A?x@?XAzB?`A?dB?l@?P?F?H@^?Z?@?H?@?Z?h@?f@?j@?^?t@@j@BnAAV@|@@fB?bBG?"}, "start_location": {"lat": 29.800614, "lng": -95.32835}, "transit_details": {"arrival_stop": {"location": {"lat": 29.80163, "lng": -95.454342}, "name": "W 18th St @ Northwest Fwy"}, "arrival_time": {"text": "4:03pm", "time_zone": "America/Chicago", "value": 1642025020}, "departure_stop": {"location": {"lat": 29.800614, "lng": -95.32835}, "name": "Hirsch Rd @ Cavalcade St"}, "departure_time": {"text": "3:34pm", "time_zone": "America/Chicago", "value": 1642023248}, "headsign": "Memorial City", "line": {"agencies": [{"name": "Metropolitan Transit Authority of Harris County", "phone": "1 (713) 635-4000", "url": "http://www.ridemetro.org/"}], "color": "#004080", "name": "Long Point / Cavalcade", "short_name": "26", "text_color": "#ffffff", "url": "https://www.ridemetro.org/MetroPDFs/Schedules/BusSchedules/n026-Long-Point-Cavalcade.pdf", "vehicle": {"icon": "//maps.gstatic.com/mapfiles/transit/iw2/6/bus2.png", "name": "Bus", "type": "BUS"}}, "num_stops": 46, "trip_short_name": "LONGPOINT"}, "travel_mode": "TRANSIT"}, {"distance": {"text": "322 ft", "value": 98}, "duration": {"text": "1 min", "value": 77}, "end_location": {"lat": 29.8019199, "lng": -95.45428179999999}, "html_instructions": "Walk to 4400 W 18th St, Houston, TX 77092, USA", "polyline": {"points": "es{tDrlreQ?z@YEc@E?G@Q@a@"}, "start_location": {"lat": 29.8016264, "lng": -95.454342}, "steps": [{"distance": {"text": "95 ft", "value": 29}, "duration": {"text": "1 min", "value": 22}, "end_location": {"lat": 29.8016252, "lng": -95.45463819999999}, "html_instructions": "Head <b>west</b> on <b>W 18th St</b>/<wbr/><b>NW Mall</b>", "polyline": {"points": "es{tDrlreQ?z@"}, "start_location": {"lat": 29.8016264, "lng": -95.454342}, "travel_mode": "WALKING"}, {"distance": {"text": "131 ft", "value": 40}, "duration": {"text": "1 min", "value": 33}, "end_location": {"lat": 29.8019405, "lng": -95.4545788}, "html_instructions": "Turn <b>right</b><div style=\"font-size:0.9em\">Restricted usage road</div>", "maneuver": "turn-right", "polyline": {"points": "es{tDnnreQYEc@E"}, "start_location": {"lat": 29.8016252, "lng": -95.45463819999999}, "travel_mode": "WALKING"}, {"distance": {"text": "95 ft", "value": 29}, "duration": {"text": "1 min", "value": 22}, "end_location": {"lat": 29.8019199, "lng": -95.45428179999999}, "html_instructions": "Turn <b>right</b><div style=\"font-size:0.9em\">Restricted usage road</div><div style=\"font-size:0.9em\">Destination will be on the left</div>", "maneuver": "turn-right", "polyline": {"points": "cu{tDbnreQ?G@Q@a@"}, "start_location": {"lat": 29.8019405, "lng": -95.4545788}, "travel_mode": "WALKING"}], "travel_mode": "WALKING"}], "traffic_speed_entry": [], "via_waypoint": []}], "overview_polyline": {"points": "uiztD~|wdQ{D@sED@dC@xEH`UDpUG@@P?RG?e@Bu@HiAZeB^q@Hm@Bs@@{FDy@?C@?It@??zABxHDpEFdG@zBGvAM|DWvCw@tDo@jCe@vCk@fEaA`GWjBUlBs@fGYfCc@jEo@fFc@jDYzBYdCStASbBOlCAbA@~CBfFRb[@fAGrAIpBFfPF~PDnOBhKEbDGvAa@`CYjASfAI`AMzCKjECr@ElB?rBBzHBdK@fDE`BAfA@pC@zCDpBFt@BnA@jDAjCAXShCAhJ@hFAxBOjAEhBFjIBtHPrd@HzTNv`@Rjm@BjYB|W@bABZLp@Vp@^l@x@~@hBtBf@j@^f@BJFNf@v@P`@Jr@D\\@h@@bA@|BIpB@f@?~A?bA?tB@hB@pC?zLBdWDvd@@jKA`HDbIA`F?tK?bEDpE@`HG??z@YEc@E?GBs@"}, "summary": "", "warnings": ["Walking directions are in beta. Use caution \u2013 This route may be missing sidewalks or pedestrian paths."], "waypoint_order": []}, {"bounds": {"northeast": {"lat": 29.80413, "lng": -95.3187203}, "southwest": {"lat": 29.79499329999999, "lng": -95.45463819999999}}, "copyrights": "Map data \u00a92022", "legs": [{"arrival_time": {"text": "4:19pm", "time_zone": "America/Chicago", "value": 1642025997}, "departure_time": {"text": "3:29pm", "time_zone": "America/Chicago", "value": 1642022988}, "distance": {"text": "8.7 mi", "value": 13960}, "duration": {"text": "50 mins", "value": 3009}, "end_address": "4400 W 18th St, Houston, TX 77092, USA", "end_location": {"lat": 29.8019199, "lng": -95.45428179999999}, "start_address": "3830 Pickfair St, Houston, TX 77026, USA", "start_location": {"lat": 29.79499329999999, "lng": -95.3187203}, "steps": [{"distance": {"text": "0.9 mi", "value": 1520}, "duration": {"text": "19 mins", "value": 1161}, "end_location": {"lat": 29.8005867, "lng": -95.32834079999999}, "html_instructions": "Walk to Hirsch Rd @ Cavalcade St", "polyline": {"points": "uiztD~|wdQuA@eB?sED@dC?P@fEB~ID`JB~I@tE?f@?rBG@@P?RG?I?[B_@DUBGBMBi@NIBm@NC?]HUDq@Hm@BE?m@@C?yEBM?O@M?k@?"}, "start_location": {"lat": 29.79499329999999, "lng": -95.3187203}, "steps": [{"distance": {"text": "0.1 mi", "value": 222}, "duration": {"text": "3 mins", "value": 163}, "end_location": {"lat": 29.7969855, "lng": -95.3187564}, "html_instructions": "Head <b>north</b> on <b>Pickfair St</b> toward <b>Crane St</b>", "polyline": {"points": "uiztD~|wdQuA@eB?sED"}, "start_location": {"lat": 29.79499329999999, "lng": -95.3187203}, "travel_mode": "WALKING"}, {"distance": {"text": "0.5 mi", "value": 875}, "duration": {"text": "11 mins", "value": 654}, "end_location": {"lat": 29.7969249, "lng": -95.3278594}, "html_instructions": "Turn <b>left</b> onto <b>Crane St</b>", "maneuver": "turn-left", "polyline": {"points": "evztDf}wdQ@dC?P@fEB~ID`JB~I@tE?f@?rBG@@P?R"}, "start_location": {"lat": 29.7969855, "lng": -95.3187564}, "travel_mode": "WALKING"}, {"distance": {"text": "341 ft", "value": 104}, "duration": {"text": "1 min", "value": 84}, "end_location": {"lat": 29.7977888, "lng": -95.328069}, "html_instructions": "Turn <b>right</b> onto <b>Broyles St</b>", "maneuver": "turn-right", "polyline": {"points": "wuztDbvydQG?I?[B_@DUBGBMBi@NIB"}, "start_location": {"lat": 29.7969249, "lng": -95.3278594}, "travel_mode": "WALKING"}, {"distance": {"text": "0.2 mi", "value": 315}, "duration": {"text": "4 mins", "value": 257}, "end_location": {"lat": 29.8005867, "lng": -95.32834079999999}, "html_instructions": "Continue straight onto <b>Hirsch Rd</b>", "maneuver": "straight", "polyline": {"points": "e{ztDlwydQm@NC?]HUDq@Hm@BE?m@@C?yEBM?O@M?k@?"}, "start_location": {"lat": 29.7977888, "lng": -95.328069}, "travel_mode": "WALKING"}, {"distance": {"text": "13 ft", "value": 4}, "duration": {"text": "1 min", "value": 3}, "end_location": {"lat": 29.8005867, "lng": -95.32834079999999}, "html_instructions": "Turn <b>left</b><div style=\"font-size:0.9em\">Destination will be on the right</div>", "maneuver": "turn-left", "polyline": {"points": "ul{tDbyydQ"}, "start_location": {"lat": 29.8005867, "lng": -95.32834079999999}, "travel_mode": "WALKING"}], "travel_mode": "WALKING"}, {"distance": {"text": "7.7 mi", "value": 12342}, "duration": {"text": "30 mins", "value": 1772}, "end_location": {"lat": 29.80163, "lng": -95.454342}, "html_instructions": "Bus towards Memorial City", "polyline": {"points": "yl{tDdyydQ?It@??n@?j@@bD?p@@hA?X?x@DvCFpD?rA@zBGvAEpAGjBARC\\K`AEb@]fBKb@EPGVYdAUdAMx@W|AOjAMx@EZGd@WbBKj@Ib@EVAFIf@ADKn@Kz@In@K|@SdBK|@Gb@K~@AHW|Bc@jEo@fFWlBK|@EVSbBQpAGr@Mp@Eb@CNOrAKdBCf@?HAx@?xB@d@@j@?pA@nA?X@dB?T@fAB~D@bD@ZBbEBzB@fAGrAAXGvA@vD@xC@^@tD@x@?V?v@?l@?\\BpD@nB?fA@jA?tA?T?\\?lA@nA?tA@dA?Z@bA?pB@vDAlBAV?LANAT?RAXCR?@CXQ|@Kf@Sz@ENOr@CRE\\Cb@KfCARCpAAv@AXCf@?DAT?LAHCfAAd@?D?lB?h@?VBjC?lB?x@@z@@fB?fD@fDE`BA|@?HA\\@V?lA@L?\\?x@?V@j@@t@?L?JB`@@T@NBN@N@V?f@@f@?`A?r@?L?xBAP?JALAPANIbAEb@?TAR?V?fH?p@@vD@xAC^C^CRA@ETC\\Af@?P?P?LA`@@\\BpA?^@j@?H@tA?n@?b@@b@?X?P?V@`A?v@@dA?V?vA@T?lB@jB@tA?XB|E?~A@zB@nB?V?V@t@?L?R?L@R?N?f@?h@@|@?\\?d@?b@@n@?pA@|B?d@?`@@t@?T?pA@v@@rA?v@@bD@~@?nA@H?tB@^@dC?P?j@@x@?x@?t@@P?dA@|A?\\?^@dC@zB?xA?N@V?fA@`ABfE?tABtJ?pB@rA?r@?H?|@?jB?@?j@@h@AL?\\?J@f@?|B?h@?|@?n@?N?|G?J@tE?d@@dC?p@AL@J?V@P@H?B?D@F@HBH@JDPDLDLDHDJDJHLFHFHLL?@TVTVn@v@NRh@h@NPVX^f@BJBFBFf@v@P`@DZDVBT@F?D@F?H?P@P?X?N?F?j@@pAIpB@f@?V?fA?j@?V@h@AjA?h@@~@?b@@^Af@@d@?X?bA?jA?b@@nC?J?d@Aj@?v@?P@dB?jA?bC?`A?\\@dH?`D?dC@fE?jD?T@`F@vB?jD?vC?X?`E@V@zCAb@?fAAX@fB@fA?T@|B?l@A~A?x@?XAzB?`A?dB?l@?P?F?H@^?Z?@?H?@?Z?h@?f@?j@?^?t@@j@BnAAV@|@@fB?bBG?"}, "start_location": {"lat": 29.800614, "lng": -95.32835}, "transit_details": {"arrival_stop": {"location": {"lat": 29.80163, "lng": -95.454342}, "name": "W 18th St @ Northwest Fwy"}, "arrival_time": {"text": "4:18pm", "time_zone": "America/Chicago", "value": 1642025920}, "departure_stop": {"location": {"lat": 29.800614, "lng": -95.32835}, "name": "Hirsch Rd @ Cavalcade St"}, "departure_time": {"text": "3:49pm", "time_zone": "America/Chicago", "value": 1642024148}, "headsign": "Memorial City", "line": {"agencies": [{"name": "Metropolitan Transit Authority of Harris County", "phone": "1 (713) 635-4000", "url": "http://www.ridemetro.org/"}], "color": "#004080", "name": "Long Point / Cavalcade", "short_name": "26", "text_color": "#ffffff", "url": "https://www.ridemetro.org/MetroPDFs/Schedules/BusSchedules/n026-Long-Point-Cavalcade.pdf", "vehicle": {"icon": "//maps.gstatic.com/mapfiles/transit/iw2/6/bus2.png", "name": "Bus", "type": "BUS"}}, "num_stops": 46, "trip_short_name": "LONGPOINT"}, "travel_mode": "TRANSIT"}, {"distance": {"text": "322 ft", "value": 98}, "duration": {"text": "1 min", "value": 77}, "end_location": {"lat": 29.8019199, "lng": -95.45428179999999}, "html_instructions": "Walk to 4400 W 18th St, Houston, TX 77092, USA", "polyline": {"points": "es{tDrlreQ?z@YEc@E?G@Q@a@"}, "start_location": {"lat": 29.8016264, "lng": -95.454342}, "steps": [{"distance": {"text": "95 ft", "value": 29}, "duration": {"text": "1 min", "value": 22}, "end_location": {"lat": 29.8016252, "lng": -95.45463819999999}, "html_instructions": "Head <b>west</b> on <b>W 18th St</b>/<wbr/><b>NW Mall</b>", "polyline": {"points": "es{tDrlreQ?z@"}, "start_location": {"lat": 29.8016264, "lng": -95.454342}, "travel_mode": "WALKING"}, {"distance": {"text": "131 ft", "value": 40}, "duration": {"text": "1 min", "value": 33}, "end_location": {"lat": 29.8019405, "lng": -95.4545788}, "html_instructions": "Turn <b>right</b><div style=\"font-size:0.9em\">Restricted usage road</div>", "maneuver": "turn-right", "polyline": {"points": "es{tDnnreQYEc@E"}, "start_location": {"lat": 29.8016252, "lng": -95.45463819999999}, "travel_mode": "WALKING"}, {"distance": {"text": "95 ft", "value": 29}, "duration": {"text": "1 min", "value": 22}, "end_location": {"lat": 29.8019199, "lng": -95.45428179999999}, "html_instructions": "Turn <b>right</b><div style=\"font-size:0.9em\">Restricted usage road</div><div style=\"font-size:0.9em\">Destination will be on the left</div>", "maneuver": "turn-right", "polyline": {"points": "cu{tDbnreQ?G@Q@a@"}, "start_location": {"lat": 29.8019405, "lng": -95.4545788}, "travel_mode": "WALKING"}], "travel_mode": "WALKING"}], "traffic_speed_entry": [], "via_waypoint": []}], "overview_polyline": {"points": "uiztD~|wdQ{D@sED@dC@xEH`UDpUG@@P?RG?e@Bu@HiAZeB^q@Hm@Bs@@{FDy@?C@?It@??zABxHDpEFdG@zBGvAM|DWvCw@tDo@jCe@vCk@fEaA`GWjBUlBs@fGYfCc@jEo@fFc@jDYzBYdCStASbBOlCAbA@~CBfFRb[@fAGrAIpBFfPF~PDnOBhKEbDGvAa@`CYjASfAI`AMzCKjECr@ElB?rBBzHBdK@fDE`BAfA@pC@zCDpBFt@BnA@jDAjCAXShCAhJ@hFAxBOjAEhBFjIBtHPrd@HzTNv`@Rjm@BjYB|W@bABZLp@Vp@^l@x@~@hBtBf@j@^f@BJFNf@v@P`@Jr@D\\@h@@bA@|BIpB@f@?~A?bA?tB@hB@pC?zLBdWDvd@@jKA`HDbIA`F?tK?bEDpE@`HG??z@YEc@E?GBs@"}, "summary": "", "warnings": ["Walking directions are in beta. Use caution \u2013 This route may be missing sidewalks or pedestrian paths."], "waypoint_order": []}, {"bounds": {"northeast": {"lat": 29.80413, "lng": -95.3187203}, "southwest": {"lat": 29.79499329999999, "lng": -95.45463819999999}}, "copyrights": "Map data \u00a92022", "legs": [{"arrival_time": {"text": "4:34pm", "time_zone": "America/Chicago", "value": 1642026897}, "departure_time": {"text": "3:44pm", "time_zone": "America/Chicago", "value": 1642023888}, "distance": {"text": "8.7 mi", "value": 13960}, "duration": {"text": "50 mins", "value": 3009}, "end_address": "4400 W 18th St, Houston, TX 77092, USA", "end_location": {"lat": 29.8019199, "lng": -95.45428179999999}, "start_address": "3830 Pickfair St, Houston, TX 77026, USA", "start_location": {"lat": 29.79499329999999, "lng": -95.3187203}, "steps": [{"distance": {"text": "0.9 mi", "value": 1520}, "duration": {"text": "19 mins", "value": 1161}, "end_location": {"lat": 29.8005867, "lng": -95.32834079999999}, "html_instructions": "Walk to Hirsch Rd @ Cavalcade St", "polyline": {"points": "uiztD~|wdQuA@eB?sED@dC?P@fEB~ID`JB~I@tE?f@?rBG@@P?RG?I?[B_@DUBGBMBi@NIBm@NC?]HUDq@Hm@BE?m@@C?yEBM?O@M?k@?"}, "start_location": {"lat": 29.79499329999999, "lng": -95.3187203}, "steps": [{"distance": {"text": "0.1 mi", "value": 222}, "duration": {"text": "3 mins", "value": 163}, "end_location": {"lat": 29.7969855, "lng": -95.3187564}, "html_instructions": "Head <b>north</b> on <b>Pickfair St</b> toward <b>Crane St</b>", "polyline": {"points": "uiztD~|wdQuA@eB?sED"}, "start_location": {"lat": 29.79499329999999, "lng": -95.3187203}, "travel_mode": "WALKING"}, {"distance": {"text": "0.5 mi", "value": 875}, "duration": {"text": "11 mins", "value": 654}, "end_location": {"lat": 29.7969249, "lng": -95.3278594}, "html_instructions": "Turn <b>left</b> onto <b>Crane St</b>", "maneuver": "turn-left", "polyline": {"points": "evztDf}wdQ@dC?P@fEB~ID`JB~I@tE?f@?rBG@@P?R"}, "start_location": {"lat": 29.7969855, "lng": -95.3187564}, "travel_mode": "WALKING"}, {"distance": {"text": "341 ft", "value": 104}, "duration": {"text": "1 min", "value": 84}, "end_location": {"lat": 29.7977888, "lng": -95.328069}, "html_instructions": "Turn <b>right</b> onto <b>Broyles St</b>", "maneuver": "turn-right", "polyline": {"points": "wuztDbvydQG?I?[B_@DUBGBMBi@NIB"}, "start_location": {"lat": 29.7969249, "lng": -95.3278594}, "travel_mode": "WALKING"}, {"distance": {"text": "0.2 mi", "value": 315}, "duration": {"text": "4 mins", "value": 257}, "end_location": {"lat": 29.8005867, "lng": -95.32834079999999}, "html_instructions": "Continue straight onto <b>Hirsch Rd</b>", "maneuver": "straight", "polyline": {"points": "e{ztDlwydQm@NC?]HUDq@Hm@BE?m@@C?yEBM?O@M?k@?"}, "start_location": {"lat": 29.7977888, "lng": -95.328069}, "travel_mode": "WALKING"}, {"distance": {"text": "13 ft", "value": 4}, "duration": {"text": "1 min", "value": 3}, "end_location": {"lat": 29.8005867, "lng": -95.32834079999999}, "html_instructions": "Turn <b>left</b><div style=\"font-size:0.9em\">Destination will be on the right</div>", "maneuver": "turn-left", "polyline": {"points": "ul{tDbyydQ"}, "start_location": {"lat": 29.8005867, "lng": -95.32834079999999}, "travel_mode": "WALKING"}], "travel_mode": "WALKING"}, {"distance": {"text": "7.7 mi", "value": 12342}, "duration": {"text": "30 mins", "value": 1772}, "end_location": {"lat": 29.80163, "lng": -95.454342}, "html_instructions": "Bus towards Memorial City", "polyline": {"points": "yl{tDdyydQ?It@??n@?j@@bD?p@@hA?X?x@DvCFpD?rA@zBGvAEpAGjBARC\\K`AEb@]fBKb@EPGVYdAUdAMx@W|AOjAMx@EZGd@WbBKj@Ib@EVAFIf@ADKn@Kz@In@K|@SdBK|@Gb@K~@AHW|Bc@jEo@fFWlBK|@EVSbBQpAGr@Mp@Eb@CNOrAKdBCf@?HAx@?xB@d@@j@?pA@nA?X@dB?T@fAB~D@bD@ZBbEBzB@fAGrAAXGvA@vD@xC@^@tD@x@?V?v@?l@?\\BpD@nB?fA@jA?tA?T?\\?lA@nA?tA@dA?Z@bA?pB@vDAlBAV?LANAT?RAXCR?@CXQ|@Kf@Sz@ENOr@CRE\\Cb@KfCARCpAAv@AXCf@?DAT?LAHCfAAd@?D?lB?h@?VBjC?lB?x@@z@@fB?fD@fDE`BA|@?HA\\@V?lA@L?\\?x@?V@j@@t@?L?JB`@@T@NBN@N@V?f@@f@?`A?r@?L?xBAP?JALAPANIbAEb@?TAR?V?fH?p@@vD@xAC^C^CRA@ETC\\Af@?P?P?LA`@@\\BpA?^@j@?H@tA?n@?b@@b@?X?P?V@`A?v@@dA?V?vA@T?lB@jB@tA?XB|E?~A@zB@nB?V?V@t@?L?R?L@R?N?f@?h@@|@?\\?d@?b@@n@?pA@|B?d@?`@@t@?T?pA@v@@rA?v@@bD@~@?nA@H?tB@^@dC?P?j@@x@?x@?t@@P?dA@|A?\\?^@dC@zB?xA?N@V?fA@`ABfE?tABtJ?pB@rA?r@?H?|@?jB?@?j@@h@AL?\\?J@f@?|B?h@?|@?n@?N?|G?J@tE?d@@dC?p@AL@J?V@P@H?B?D@F@HBH@JDPDLDLDHDJDJHLFHFHLL?@TVTVn@v@NRh@h@NPVX^f@BJBFBFf@v@P`@DZDVBT@F?D@F?H?P@P?X?N?F?j@@pAIpB@f@?V?fA?j@?V@h@AjA?h@@~@?b@@^Af@@d@?X?bA?jA?b@@nC?J?d@Aj@?v@?P@dB?jA?bC?`A?\\@dH?`D?dC@fE?jD?T@`F@vB?jD?vC?X?`E@V@zCAb@?fAAX@fB@fA?T@|B?l@A~A?x@?XAzB?`A?dB?l@?P?F?H@^?Z?@?H?@?Z?h@?f@?j@?^?t@@j@BnAAV@|@@fB?bBG?"}, "start_location": {"lat": 29.800614, "lng": -95.32835}, "transit_details": {"arrival_stop": {"location": {"lat": 29.80163, "lng": -95.454342}, "name": "W 18th St @ Northwest Fwy"}, "arrival_time": {"text": "4:33pm", "time_zone": "America/Chicago", "value": 1642026820}, "departure_stop": {"location": {"lat": 29.800614, "lng": -95.32835}, "name": "Hirsch Rd @ Cavalcade St"}, "departure_time": {"text": "4:04pm", "time_zone": "America/Chicago", "value": 1642025048}, "headsign": "Memorial City", "line": {"agencies": [{"name": "Metropolitan Transit Authority of Harris County", "phone": "1 (713) 635-4000", "url": "http://www.ridemetro.org/"}], "color": "#004080", "name": "Long Point / Cavalcade", "short_name": "26", "text_color": "#ffffff", "url": "https://www.ridemetro.org/MetroPDFs/Schedules/BusSchedules/n026-Long-Point-Cavalcade.pdf", "vehicle": {"icon": "//maps.gstatic.com/mapfiles/transit/iw2/6/bus2.png", "name": "Bus", "type": "BUS"}}, "num_stops": 46, "trip_short_name": "LONGPOINT"}, "travel_mode": "TRANSIT"}, {"distance": {"text": "322 ft", "value": 98}, "duration": {"text": "1 min", "value": 77}, "end_location": {"lat": 29.8019199, "lng": -95.45428179999999}, "html_instructions": "Walk to 4400 W 18th St, Houston, TX 77092, USA", "polyline": {"points": "es{tDrlreQ?z@YEc@E?G@Q@a@"}, "start_location": {"lat": 29.8016264, "lng": -95.454342}, "steps": [{"distance": {"text": "95 ft", "value": 29}, "duration": {"text": "1 min", "value": 22}, "end_location": {"lat": 29.8016252, "lng": -95.45463819999999}, "html_instructions": "Head <b>west</b> on <b>W 18th St</b>/<wbr/><b>NW Mall</b>", "polyline": {"points": "es{tDrlreQ?z@"}, "start_location": {"lat": 29.8016264, "lng": -95.454342}, "travel_mode": "WALKING"}, {"distance": {"text": "131 ft", "value": 40}, "duration": {"text": "1 min", "value": 33}, "end_location": {"lat": 29.8019405, "lng": -95.4545788}, "html_instructions": "Turn <b>right</b><div style=\"font-size:0.9em\">Restricted usage road</div>", "maneuver": "turn-right", "polyline": {"points": "es{tDnnreQYEc@E"}, "start_location": {"lat": 29.8016252, "lng": -95.45463819999999}, "travel_mode": "WALKING"}, {"distance": {"text": "95 ft", "value": 29}, "duration": {"text": "1 min", "value": 22}, "end_location": {"lat": 29.8019199, "lng": -95.45428179999999}, "html_instructions": "Turn <b>right</b><div style=\"font-size:0.9em\">Restricted usage road</div><div style=\"font-size:0.9em\">Destination will be on the left</div>", "maneuver": "turn-right", "polyline": {"points": "cu{tDbnreQ?G@Q@a@"}, "start_location": {"lat": 29.8019405, "lng": -95.4545788}, "travel_mode": "WALKING"}], "travel_mode": "WALKING"}], "traffic_speed_entry": [], "via_waypoint": []}], "overview_polyline": {"points": "uiztD~|wdQ{D@sED@dC@xEH`UDpUG@@P?RG?e@Bu@HiAZeB^q@Hm@Bs@@{FDy@?C@?It@??zABxHDpEFdG@zBGvAM|DWvCw@tDo@jCe@vCk@fEaA`GWjBUlBs@fGYfCc@jEo@fFc@jDYzBYdCStASbBOlCAbA@~CBfFRb[@fAGrAIpBFfPF~PDnOBhKEbDGvAa@`CYjASfAI`AMzCKjECr@ElB?rBBzHBdK@fDE`BAfA@pC@zCDpBFt@BnA@jDAjCAXShCAhJ@hFAxBOjAEhBFjIBtHPrd@HzTNv`@Rjm@BjYB|W@bABZLp@Vp@^l@x@~@hBtBf@j@^f@BJFNf@v@P`@Jr@D\\@h@@bA@|BIpB@f@?~A?bA?tB@hB@pC?zLBdWDvd@@jKA`HDbIA`F?tK?bEDpE@`HG??z@YEc@E?GBs@"}, "summary": "", "warnings": ["Walking directions are in beta. Use caution \u2013 This route may be missing sidewalks or pedestrian paths."], "waypoint_order": []}, {"bounds": {"northeast": {"lat": 29.80413, "lng": -95.3187203}, "southwest": {"lat": 29.79499329999999, "lng": -95.45463819999999}}, "copyrights": "Map data \u00a92022", "legs": [{"arrival_time": {"text": "4:49pm", "time_zone": "America/Chicago", "value": 1642027797}, "departure_time": {"text": "3:59pm", "time_zone": "America/Chicago", "value": 1642024788}, "distance": {"text": "8.7 mi", "value": 13960}, "duration": {"text": "50 mins", "value": 3009}, "end_address": "4400 W 18th St, Houston, TX 77092, USA", "end_location": {"lat": 29.8019199, "lng": -95.45428179999999}, "start_address": "3830 Pickfair St, Houston, TX 77026, USA", "start_location": {"lat": 29.79499329999999, "lng": -95.3187203}, "steps": [{"distance": {"text": "0.9 mi", "value": 1520}, "duration": {"text": "19 mins", "value": 1161}, "end_location": {"lat": 29.8005867, "lng": -95.32834079999999}, "html_instructions": "Walk to Hirsch Rd @ Cavalcade St", "polyline": {"points": "uiztD~|wdQuA@eB?sED@dC?P@fEB~ID`JB~I@tE?f@?rBG@@P?RG?I?[B_@DUBGBMBi@NIBm@NC?]HUDq@Hm@BE?m@@C?yEBM?O@M?k@?"}, "start_location": {"lat": 29.79499329999999, "lng": -95.3187203}, "steps": [{"distance": {"text": "0.1 mi", "value": 222}, "duration": {"text": "3 mins", "value": 163}, "end_location": {"lat": 29.7969855, "lng": -95.3187564}, "html_instructions": "Head <b>north</b> on <b>Pickfair St</b> toward <b>Crane St</b>", "polyline": {"points": "uiztD~|wdQuA@eB?sED"}, "start_location": {"lat": 29.79499329999999, "lng": -95.3187203}, "travel_mode": "WALKING"}, {"distance": {"text": "0.5 mi", "value": 875}, "duration": {"text": "11 mins", "value": 654}, "end_location": {"lat": 29.7969249, "lng": -95.3278594}, "html_instructions": "Turn <b>left</b> onto <b>Crane St</b>", "maneuver": "turn-left", "polyline": {"points": "evztDf}wdQ@dC?P@fEB~ID`JB~I@tE?f@?rBG@@P?R"}, "start_location": {"lat": 29.7969855, "lng": -95.3187564}, "travel_mode": "WALKING"}, {"distance": {"text": "341 ft", "value": 104}, "duration": {"text": "1 min", "value": 84}, "end_location": {"lat": 29.7977888, "lng": -95.328069}, "html_instructions": "Turn <b>right</b> onto <b>Broyles St</b>", "maneuver": "turn-right", "polyline": {"points": "wuztDbvydQG?I?[B_@DUBGBMBi@NIB"}, "start_location": {"lat": 29.7969249, "lng": -95.3278594}, "travel_mode": "WALKING"}, {"distance": {"text": "0.2 mi", "value": 315}, "duration": {"text": "4 mins", "value": 257}, "end_location": {"lat": 29.8005867, "lng": -95.32834079999999}, "html_instructions": "Continue straight onto <b>Hirsch Rd</b>", "maneuver": "straight", "polyline": {"points": "e{ztDlwydQm@NC?]HUDq@Hm@BE?m@@C?yEBM?O@M?k@?"}, "start_location": {"lat": 29.7977888, "lng": -95.328069}, "travel_mode": "WALKING"}, {"distance": {"text": "13 ft", "value": 4}, "duration": {"text": "1 min", "value": 3}, "end_location": {"lat": 29.8005867, "lng": -95.32834079999999}, "html_instructions": "Turn <b>left</b><div style=\"font-size:0.9em\">Destination will be on the right</div>", "maneuver": "turn-left", "polyline": {"points": "ul{tDbyydQ"}, "start_location": {"lat": 29.8005867, "lng": -95.32834079999999}, "travel_mode": "WALKING"}], "travel_mode": "WALKING"}, {"distance": {"text": "7.7 mi", "value": 12342}, "duration": {"text": "30 mins", "value": 1772}, "end_location": {"lat": 29.80163, "lng": -95.454342}, "html_instructions": "Bus towards Memorial City", "polyline": {"points": "yl{tDdyydQ?It@??n@?j@@bD?p@@hA?X?x@DvCFpD?rA@zBGvAEpAGjBARC\\K`AEb@]fBKb@EPGVYdAUdAMx@W|AOjAMx@EZGd@WbBKj@Ib@EVAFIf@ADKn@Kz@In@K|@SdBK|@Gb@K~@AHW|Bc@jEo@fFWlBK|@EVSbBQpAGr@Mp@Eb@CNOrAKdBCf@?HAx@?xB@d@@j@?pA@nA?X@dB?T@fAB~D@bD@ZBbEBzB@fAGrAAXGvA@vD@xC@^@tD@x@?V?v@?l@?\\BpD@nB?fA@jA?tA?T?\\?lA@nA?tA@dA?Z@bA?pB@vDAlBAV?LANAT?RAXCR?@CXQ|@Kf@Sz@ENOr@CRE\\Cb@KfCARCpAAv@AXCf@?DAT?LAHCfAAd@?D?lB?h@?VBjC?lB?x@@z@@fB?fD@fDE`BA|@?HA\\@V?lA@L?\\?x@?V@j@@t@?L?JB`@@T@NBN@N@V?f@@f@?`A?r@?L?xBAP?JALAPANIbAEb@?TAR?V?fH?p@@vD@xAC^C^CRA@ETC\\Af@?P?P?LA`@@\\BpA?^@j@?H@tA?n@?b@@b@?X?P?V@`A?v@@dA?V?vA@T?lB@jB@tA?XB|E?~A@zB@nB?V?V@t@?L?R?L@R?N?f@?h@@|@?\\?d@?b@@n@?pA@|B?d@?`@@t@?T?pA@v@@rA?v@@bD@~@?nA@H?tB@^@dC?P?j@@x@?x@?t@@P?dA@|A?\\?^@dC@zB?xA?N@V?fA@`ABfE?tABtJ?pB@rA?r@?H?|@?jB?@?j@@h@AL?\\?J@f@?|B?h@?|@?n@?N?|G?J@tE?d@@dC?p@AL@J?V@P@H?B?D@F@HBH@JDPDLDLDHDJDJHLFHFHLL?@TVTVn@v@NRh@h@NPVX^f@BJBFBFf@v@P`@DZDVBT@F?D@F?H?P@P?X?N?F?j@@pAIpB@f@?V?fA?j@?V@h@AjA?h@@~@?b@@^Af@@d@?X?bA?jA?b@@nC?J?d@Aj@?v@?P@dB?jA?bC?`A?\\@dH?`D?dC@fE?jD?T@`F@vB?jD?vC?X?`E@V@zCAb@?fAAX@fB@fA?T@|B?l@A~A?x@?XAzB?`A?dB?l@?P?F?H@^?Z?@?H?@?Z?h@?f@?j@?^?t@@j@BnAAV@|@@fB?bBG?"}, "start_location": {"lat": 29.800614, "lng": -95.32835}, "transit_details": {"arrival_stop": {"location": {"lat": 29.80163, "lng": -95.454342}, "name": "W 18th St @ Northwest Fwy"}, "arrival_time": {"text": "4:48pm", "time_zone": "America/Chicago", "value": 1642027720}, "departure_stop": {"location": {"lat": 29.800614, "lng": -95.32835}, "name": "Hirsch Rd @ Cavalcade St"}, "departure_time": {"text": "4:19pm", "time_zone": "America/Chicago", "value": 1642025948}, "headsign": "Memorial City", "line": {"agencies": [{"name": "Metropolitan Transit Authority of Harris County", "phone": "1 (713) 635-4000", "url": "http://www.ridemetro.org/"}], "color": "#004080", "name": "Long Point / Cavalcade", "short_name": "26", "text_color": "#ffffff", "url": "https://www.ridemetro.org/MetroPDFs/Schedules/BusSchedules/n026-Long-Point-Cavalcade.pdf", "vehicle": {"icon": "//maps.gstatic.com/mapfiles/transit/iw2/6/bus2.png", "name": "Bus", "type": "BUS"}}, "num_stops": 46, "trip_short_name": "LONGPOINT"}, "travel_mode": "TRANSIT"}, {"distance": {"text": "322 ft", "value": 98}, "duration": {"text": "1 min", "value": 77}, "end_location": {"lat": 29.8019199, "lng": -95.45428179999999}, "html_instructions": "Walk to 4400 W 18th St, Houston, TX 77092, USA", "polyline": {"points": "es{tDrlreQ?z@YEc@E?G@Q@a@"}, "start_location": {"lat": 29.8016264, "lng": -95.454342}, "steps": [{"distance": {"text": "95 ft", "value": 29}, "duration": {"text": "1 min", "value": 22}, "end_location": {"lat": 29.8016252, "lng": -95.45463819999999}, "html_instructions": "Head <b>west</b> on <b>W 18th St</b>/<wbr/><b>NW Mall</b>", "polyline": {"points": "es{tDrlreQ?z@"}, "start_location": {"lat": 29.8016264, "lng": -95.454342}, "travel_mode": "WALKING"}, {"distance": {"text": "131 ft", "value": 40}, "duration": {"text": "1 min", "value": 33}, "end_location": {"lat": 29.8019405, "lng": -95.4545788}, "html_instructions": "Turn <b>right</b><div style=\"font-size:0.9em\">Restricted usage road</div>", "maneuver": "turn-right", "polyline": {"points": "es{tDnnreQYEc@E"}, "start_location": {"lat": 29.8016252, "lng": -95.45463819999999}, "travel_mode": "WALKING"}, {"distance": {"text": "95 ft", "value": 29}, "duration": {"text": "1 min", "value": 22}, "end_location": {"lat": 29.8019199, "lng": -95.45428179999999}, "html_instructions": "Turn <b>right</b><div style=\"font-size:0.9em\">Restricted usage road</div><div style=\"font-size:0.9em\">Destination will be on the left</div>", "maneuver": "turn-right", "polyline": {"points": "cu{tDbnreQ?G@Q@a@"}, "start_location": {"lat": 29.8019405, "lng": -95.4545788}, "travel_mode": "WALKING"}], "travel_mode": "WALKING"}], "traffic_speed_entry": [], "via_waypoint": []}], "overview_polyline": {"points": "uiztD~|wdQ{D@sED@dC@xEH`UDpUG@@P?RG?e@Bu@HiAZeB^q@Hm@Bs@@{FDy@?C@?It@??zABxHDpEFdG@zBGvAM|DWvCw@tDo@jCe@vCk@fEaA`GWjBUlBs@fGYfCc@jEo@fFc@jDYzBYdCStASbBOlCAbA@~CBfFRb[@fAGrAIpBFfPF~PDnOBhKEbDGvAa@`CYjASfAI`AMzCKjECr@ElB?rBBzHBdK@fDE`BAfA@pC@zCDpBFt@BnA@jDAjCAXShCAhJ@hFAxBOjAEhBFjIBtHPrd@HzTNv`@Rjm@BjYB|W@bABZLp@Vp@^l@x@~@hBtBf@j@^f@BJFNf@v@P`@Jr@D\\@h@@bA@|BIpB@f@?~A?bA?tB@hB@pC?zLBdWDvd@@jKA`HDbIA`F?tK?bEDpE@`HG??z@YEc@E?GBs@"}, "summary": "", "warnings": ["Walking directions are in beta. Use caution \u2013 This route may be missing sidewalks or pedestrian paths."], "waypoint_order": []}], "status": "OK"}